cache_cleaner/__init__.py
cache_cleaner/cli.py
cache_cleaner/core.py
deep_cache_cleaner-1.0.1.dist-info/licenses/LICENSE
deep_cache_cleaner-1.0.1.dist-info/METADATA
deep_cache_cleaner-1.0.1.dist-info/WHEEL
deep_cache_cleaner-1.0.1.dist-info/entry_points.txt
deep_cache_cleaner-1.0.1.dist-info/top_level.txt
deep_cache_cleaner-1.0.1.dist-info/RECORD
