Metadata-Version: 2.4
Name: deep-cache-cleaner
Version: 1.0.1
Summary: Comprehensive cache clearing utility for PyTorch, HuggingFace, and other ML libraries
Author-email: Mihai Badea <mmihai.badea@gmail.com>
Maintainer-email: Mihai Badea <mmihai.badea@gmail.com>
License-Expression: MIT
Project-URL: Homepage, https://github.com/mbaxamb33/deep-cache-cleaner
Project-URL: Documentation, https://github.com/mbaxamb33/deep-cache-cleaner#readme
Project-URL: Repository, https://github.com/mbaxamb33/deep-cache-cleaner
Project-URL: Bug Tracker, https://github.com/mbaxamb33/deep-cache-cleaner/issues
Keywords: cache,pytorch,huggingface,ml,cleanup,memory
Classifier: Development Status :: 4 - Beta
Classifier: Intended Audience :: Developers
Classifier: Operating System :: OS Independent
Classifier: Programming Language :: Python :: 3
Classifier: Programming Language :: Python :: 3.8
Classifier: Programming Language :: Python :: 3.9
Classifier: Programming Language :: Python :: 3.10
Classifier: Programming Language :: Python :: 3.11
Classifier: Programming Language :: Python :: 3.12
Classifier: Topic :: Software Development :: Libraries :: Python Modules
Classifier: Topic :: System :: Systems Administration
Requires-Python: >=3.8
License-File: LICENSE
Provides-Extra: gpu
Requires-Dist: torch>=1.9.0; extra == "gpu"
Provides-Extra: transformers
Requires-Dist: transformers>=4.0.0; extra == "transformers"
Provides-Extra: sentence-transformers
Requires-Dist: sentence-transformers>=2.0.0; extra == "sentence-transformers"
Provides-Extra: all
Requires-Dist: torch>=1.9.0; extra == "all"
Requires-Dist: transformers>=4.0.0; extra == "all"
Requires-Dist: sentence-transformers>=2.0.0; extra == "all"
Provides-Extra: dev
Requires-Dist: pytest>=6.0; extra == "dev"
Requires-Dist: pytest-cov; extra == "dev"
Requires-Dist: black; extra == "dev"
Requires-Dist: flake8; extra == "dev"
Requires-Dist: mypy; extra == "dev"
Dynamic: license-file
